{"swagger":"2.0","basePath":"","info":{"title":"Exchange","version":"1.0.0","description":"Converts crypto to fiat"},"schemes":null,"consumes":["application/json"],"produces":["application/json"],"paths":{"/api/batch-exchange/{amount}/{currencies}":{"get":{"operationId":"BatchConvert","parameters":[{"description":"The amount of crypto to convert","format":"float","in":"path","name":"amount","required":true,"type":"number"},{"collectionFormat":"csv","description":"The currencies to convert the crypto amount to","in":"path","items":{"type":"string"},"minItems":1,"name":"currencies","required":true,"type":"array"}],"responses":{"200":{"description":"A successful response.","schema":{"$ref":"#/definitions/exchangeBatchConvertResponse"}},"default":{"description":"An unexpected error response.","schema":{"$ref":"#/definitions/runtimeError"}}},"summary":"BatchConvert - Convert the amount of crypto to the given currencies.","tags":["Exchange"]}},"/api/exchange/rates":{"get":{"operationId":"ListRates","parameters":[{"description":"Number of page.","format":"int32","in":"query","name":"pageId","required":false,"type":"integer"},{"description":"Number of items to return.","format":"int32","in":"query","name":"pageSize","required":false,"type":"integer"}],"responses":{"200":{"description":"A successful response.","schema":{"$ref":"#/definitions/exchangeListRatesResponse"}},"default":{"description":"An unexpected error response.","schema":{"$ref":"#/definitions/runtimeError"}}},"summary":"ListRates - listing of rates with pagination.","tags":["Exchange"]}},"/api/exchange/{amount}/{currency}":{"get":{"operationId":"Convert","parameters":[{"description":"The amount of crypto to convert","format":"float","in":"path","name":"amount","required":true,"type":"number"},{"description":"The currency to convert the crypto amount to","in":"path","name":"currency","required":true,"type":"string"}],"responses":{"200":{"description":"A successful response.","schema":{"$ref":"#/definitions/exchangeConvertResponse"}},"default":{"description":"An unexpected error response.","schema":{"$ref":"#/definitions/runtimeError"}}},"summary":"Convert - Convert the amount of crypto to the given currency.","tags":["Exchange"]}}},"definitions":{"exchangeBatchConvertResponse":{"properties":{"list":{"description":"List of converted amounts and currencies","items":{"$ref":"#/definitions/exchangeConvertResponse"},"type":"array"}},"type":"object"},"exchangeConvertResponse":{"properties":{"currency":{"description":"The currency of the fiat","type":"string"},"value":{"description":"The value of the fiat","format":"float","type":"number"}},"type":"object"},"exchangeListRatesResponse":{"properties":{"items":{"description":"List of batches","items":{"$ref":"#/definitions/exchangeRate"},"type":"array"},"nextPage":{"description":"Number of next page","format":"int32","type":"integer"}},"type":"object"},"exchangeRate":{"properties":{"conversionRate":{"description":"Conversion rate","format":"float","type":"number"},"currency":{"description":"Currency name","type":"string"}},"type":"object"},"protobufAny":{"properties":{"typeUrl":{"type":"string"},"value":{"format":"byte","type":"string"}},"type":"object"},"runtimeError":{"properties":{"code":{"format":"int32","type":"integer"},"details":{"items":{"$ref":"#/definitions/protobufAny"},"type":"array"},"error":{"type":"string"},"message":{"type":"string"}},"type":"object"}}}
